<DOCUMENT><DOCID>file856</DOCID><NATURAL_DISASTER TYPE="FLOODS"> flooded </NATURAL_DISASTER><MANMADE_DISASTER TYPE="VEHICULAR_COLLISION"> accident </MANMADE_DISASTER><NATURAL_DISASTER TYPE="FLOODS"> flooded </NATURAL_DISASTER><MANMADE_DISASTER TYPE="ACCIDENTS"> accident </MANMADE_DISASTER><NATURAL_DISASTER TYPE="EARTHQUAKE"> incidents </NATURAL_DISASTER><MANMADE_DISASTER TYPE="VEHICULAR_COLLISION"> accident </MANMADE_DISASTER><NATURAL_DISASTER TYPE="FLOODS"> floods </NATURAL_DISASTER><NATURAL_DISASTER TYPE="FLOODS"> flooded. </NATURAL_DISASTER><MANMADE_DISASTER TYPE="INDUSTRIAL_ACCIDENT"> industrial   accidents </MANMADE_DISASTER><MANMADE_DISASTER TYPE="INDUSTRIAL_ACCIDENT"> blast </MANMADE_DISASTER></DOCUMENT>