<DOCUMENT><DOCID>tamil_event_doc187</DOCID><MANMADE_DISASTER TYPE="VEHICULAR_COLLISION"> மோதிய   விபத்தில் </MANMADE_DISASTER><MANMADE_DISASTER TYPE="VEHICULAR_COLLISION"> மோதியது. </MANMADE_DISASTER><MANMADE_DISASTER TYPE="VEHICULAR_COLLISION"> விபத்தில் </MANMADE_DISASTER><MANMADE_DISASTER TYPE="VEHICULAR_COLLISION"> மோதியது. </MANMADE_DISASTER><MANMADE_DISASTER TYPE="TRANSPORT_HAZARDS"> லாரி   கவிழ்ந்து </MANMADE_DISASTER><MANMADE_DISASTER TYPE="VEHICULAR_COLLISION"> வாகன   விபத்தில் </MANMADE_DISASTER><MANMADE_DISASTER TYPE="VEHICULAR_COLLISION"> மோதியது. </MANMADE_DISASTER><MANMADE_DISASTER TYPE="VEHICULAR_COLLISION"> விபத்து </MANMADE_DISASTER><MANMADE_DISASTER TYPE="VEHICULAR_COLLISION"> விபத்தால் </MANMADE_DISASTER><MANMADE_DISASTER TYPE="ACCIDENTS"> விபத்தில் </MANMADE_DISASTER></DOCUMENT>