<DOCUMENT><DOCID>1031116_16bdesh5</DOCID><TIME> ৩০   কার্তিক   ১৪১০   রবিবার   ১৬   নভেম্বর   ২০০৩ </TIME><PARTICIPANT> দুই   মার্কিন   হেলিকপ্টারের </PARTICIPANT><MANMADE_DISASTER TYPE="ARMED_CONFLICTS"> সংঘর্ষ   মসুলে, </MANMADE_DISASTER><CASUALTIES> মৃত   ১২   সেনা </CASUALTIES><MANMADE_DISASTER TYPE="VEHICULAR_COLLISION"> সংঘর্ষে </MANMADE_DISASTER><PLACE> মসুলে </PLACE><CASUALTIES> ১২   জন   সেনার   মৃত্যু </CASUALTIES><CASUALTIES> আহত   হয়েছেন   ৯   জন।   ১০১ </CASUALTIES><MANMADE_DISASTER TYPE="AVIATION_HAZARD"> ভেঙে   পড়ে। </MANMADE_DISASTER><CASUALTIES> সাত   ইরাকি   প্রাণ   হারান। </CASUALTIES><MANMADE_DISASTER TYPE="NORMAL_BOMBING"> রকেট   হামলা </MANMADE_DISASTER></DOCUMENT>