<DOCUMENT><DOCID>file1027</DOCID><CASUALTIES> Two   injured </CASUALTIES><MANMADE_DISASTER TYPE="TRANSPORT_HAZARDS"> truck   falls </MANMADE_DISASTER><CASUALTIES> Two   men   were   injured </CASUALTIES><MANMADE_DISASTER TYPE="TRANSPORT_HAZARDS"> fell   into </MANMADE_DISASTER><PLACE> Sathyamangalam </PLACE><PLACE> Dimbam   Ghat   Road   in   the   district </PLACE><TIME> Wednesday. </TIME><MANMADE_DISASTER TYPE="VEHICULAR_COLLISION"> incident, </MANMADE_DISASTER><REASON> 40,   lost   control   over </REASON><MANMADE_DISASTER TYPE="MISCELLANEOUS"> fell </MANMADE_DISASTER></DOCUMENT>