<DOCUMENT><DOCID>file852</DOCID><CASUALTIES> Three   from   Delhi   killed,   14   injured </CASUALTIES><MANMADE_DISASTER TYPE="ACCIDENTS"> road   accident </MANMADE_DISASTER><PLACE> UP </PLACE><CASUALTIES> Three   people   were   killed   and   14   injured </CASUALTIES><MANMADE_DISASTER TYPE="VEHICULAR_COLLISION"> collision </MANMADE_DISASTER><PLACE> Delhi-Dehradun   national   highway   in   Muzaffarnagar   district, </PLACE><MANMADE_DISASTER TYPE="ACCIDENTS"> accident </MANMADE_DISASTER><PLACE> Tigai   village </PLACE><TIME> last   evening </TIME><MANMADE_DISASTER TYPE="VEHICULAR_COLLISION"> accident </MANMADE_DISASTER><CASUALTIES> Harpal   Singh   (30),   Surjit   (23)   and   Rakesh   (28). </CASUALTIES><MANMADE_DISASTER TYPE="ACCIDENTS"> accident </MANMADE_DISASTER></DOCUMENT>