<DOCUMENT><DOCID>tamil_event_doc169</DOCID><MANMADE_DISASTER TYPE="ACCIDENTS"> கார்   மோதி </MANMADE_DISASTER><CASUALTIES> 3   பேர்   பலி </CASUALTIES><PLACE> கர்நாடகா   மாநிலம்,   ஹாசன்   மாவட்டத்தில் </PLACE><PLACE> திருப்பூர்   மாவட்டம்,   வெள்ளகோவில்   அருகே, </PLACE><TIME> நேற்று   காலை,   2:45   மணிக்கு </TIME><MANMADE_DISASTER TYPE="VEHICULAR_COLLISION"> மோதியது. </MANMADE_DISASTER><CASUALTIES> இதில்   கார்   உருக்குலைந்தது.   மூவரும்   உடல்   நசுங்கி   பலியாகினர். </CASUALTIES></DOCUMENT>