<DOCUMENT><DOCID>tamil_event_doc96</DOCID><PLACE> தாராப்பூர்   ரசாயன   ஆலையில் </PLACE><MANMADE_DISASTER TYPE="FIRE"> தீ   விபத்து </MANMADE_DISASTER><CASUALTIES> 3   பேர்   உயிரிழப்பு </CASUALTIES><PLACE> மகாராஷ்டிரா   மாநிலத்தின்   பால்கர்   மாவட்டத்தில் </PLACE><PLACE> அங்குள்ள   ரசாயன   ஆலையில் </PLACE><TIME> நேற்று   இரவு </TIME><MANMADE_DISASTER TYPE="FIRE"> தீ </MANMADE_DISASTER><MANMADE_DISASTER TYPE="FIRE"> தீ   விபத்தில் </MANMADE_DISASTER><MANMADE_DISASTER TYPE="FIRE"> தீ   விபத்தில் </MANMADE_DISASTER><CASUALTIES> 3   பேர்   உடல்   கருகி   உயிரிழந்தனர்.   பலத்த   காயங்களுடன்   அனுமதிக்கப்பட்ட   14   பேர்   மருத்துவமனையில் </CASUALTIES></DOCUMENT>